ppdap/__init__.py
ppdap/attribute.py
ppdap/connection.py
ppdap/const.py
ppdap/device.py
ppdap/httpc.py
ppdap/mqttc.py
ppdap/schedule.py
ppdap/setup.py
ppdap/storage.py
ppdap/utils.py
ppdap-0.0.5.dist-info/METADATA
ppdap-0.0.5.dist-info/WHEEL
ppdap-0.0.5.dist-info/top_level.txt
ppdap-0.0.5.dist-info/RECORD
